print_tools/__init__.py
print_tools/printer.py
print_tools-0.0.5.dist-info/METADATA
print_tools-0.0.5.dist-info/RECORD
print_tools-0.0.5.dist-info/WHEEL
print_tools-0.0.5.dist-info/top_level.txt
