Metadata-Version: 2.1
Name: print-tools
Version: 0.0.5
Summary: Print styling/formatting methods.
Home-page: https://github.com/edmundpf/print_tools
Author: Edmund Pfeil
Author-email: edmundpf@buffalo.edu
License: UNKNOWN
Platform: UNKNOWN
Classifier: Programming Language :: Python :: 3
Classifier: License :: OSI Approved :: MIT License
Classifier: Operating System :: OS Independent
Requires-Dist: colorful
